scriptlock/__init__.py
scriptlock-1.0.5.dist-info/DESCRIPTION.rst
scriptlock-1.0.5.dist-info/METADATA
scriptlock-1.0.5.dist-info/RECORD
scriptlock-1.0.5.dist-info/WHEEL
scriptlock-1.0.5.dist-info/metadata.json
scriptlock-1.0.5.dist-info/top_level.txt
